{"Ethereum-Year-Badge":660542,"Scroll-Origins-NFT":266771,"Pencils-SOUL-Drops":154616,"Scroll-Reputation-Attestation":151453,"OmniHub-Badge":128059,"Ambient-Swapooor":110776,"ZNS-Badge":105934,"Proof-of-Humanity-Badge":93716,"NFTs2Me-Creator-Badge":92592,"XHS-Holder":92327,"RubyScore-ranking-on-Scroll":89271,"Unrevealed":82981,"iZiSwap-Swapper-Badge":81132,"Entry-Scroll-Bridger-Badge":66623,"Scroll-Cross-chain-Professional":64980,"Scroll-Swapper":61267,"Toaster-Airdrop-Badge":59766,"MemeBridge-Bridger":59329,"Ambient-Providoor":58031,"Scroll-cross-chain-Beginner":56214,"SyncSwap-Lucky-Trader":55360,"MiniBridge-Beginner":53720,"Eisen-Beginner":52557,"Unique-Humanity-Score":52540,"zkSync-Bridger":51503,"Symbiosis-Pro-Swapper":50206,"Arbitrum-Bridger":40763,"Base-Bridger":40025,"Scroll-Keeper-Badge":37137,"Hypo-Scroll-OG-Badge":36746,"Optimism-Bridger":35244,"Hypo-Scroll-Guardian-Badge":34957,"OmniHub-Guardian-Badge":34094,"Blast-Bridger":32139,"Linea-Bridger":32112,"Smilecobra-Genesis-Badge":31069,"MemeBridge-Bridger-Premium":30183,"Scroll-Cross-chain-Whale":28907,"Zebra":28636,"Scroll-Booster":26505,"Hippo-Badge-2":25981,"Loyal-Scroll-Bridger-Badge":25530,"Pencil-P-Badge":22553,"Mode-Bridger":22155,"Taiko-Bridger":22148,"Polygon-zkEVM-Bridger":21852,"Mantle-Bridger":21160,"Fanaticism-Scroll-Bridger-Badge":20602,"iZiSwap-Liquidity-Provider-Badge":20349,"Scroll-RetroBridger":20215,"XY-Bridge-Badge":19375,"Ambient-Filloor":18206,"Scroll-Explorer":17268,"Toaster-GM-Badge":15649,"OmniHub-Profile-Badge":15580,"Conft-Scroll-Box":15409,"NFTs2Me-Supporter-Badge":15123,"Nuri-Locker-Badge-(10)":14462,"Smilecobra-Genleap-Badge":14176,"Eisen-Explorer":13663,"Human-Squad-with-DMAIL":11794,"SyncSwap-Stargazer":11557,"Bronze-Scroll-Bridger-Badge":10544,"Scroll-Galaxy-Rover":10544,"Scroll-C2-Portal":10330,"Lazy-Sloth-Badge":10309,"Conft-2024-Badge":9732,"XY-Liquidity-Badge":9710,"Interport-Cross-Chain-Swapper":9631,"Interport-Gas-Booster":8156,"Across-x-Toaster-Collab-Badge":7977,"Scroller-Agent-Badge":7886,"NFTs2Me-Bronze-Pin-Badge":7667,"Scroll-Galaxy-Navigator":7349,"Swapping-Sorcerer":7138,"Scroll-C2-1stJourney":7088,"Pencil-S-Badge":6720,"Human-Squad-with-Izumi":6289,"Scroll-C2-1stUGCExp":5977,"Explorer-Certificate":5464,"Matcha-Scroll-Trader":5445,"MiniBridge-Silver":5344,"Scroll-C2-Living":5313,"OmniHub-Gold-Badge":5009,"Highlight-Singularity-Badge":4896,"Scroll-MasterBridger":4724,"Gold-Scroll-Bridger-Badge":4145,"Landing-on-Scroll":4009,"Meta-Map-Scout-Badge":3871,"Across-x-Toaster-Collab-Badge-Pro":3869,"Liquidity-Loremaster":3665,"Xstar-Human-Squad-with-Rhino":3661,"Deferred-transaction-service-from-RubyScore-on-Scroll":3661,"Rookie-Badge":3591,"Comet-Bridger-Badge":3550,"Scroll-Domain-Master-Badge-\ud83c\udf96\ufe0f":3490,"oooo-Pioneer":3237,"Venister-Badge":3209,"Interport-Space-Cadet":3179,"MiniBridge-Champion":3068,"Toaster-Degen-Badge":2627,"Interport-Stellar-Bridger":2583,"Toaster-OG-Badge":2503,"Vessel-Voyager":2483,"Comet-Bridger-Badge-Pre":2271,"Eisen-Tier-2-Navigator":2234,"Hippo-Realm-Holder":2126,"Eisen-Tier-1-Pioneer":2036,"Wardseal-Wizard":1994,"Scroll-MasterSwapper":1926,"oooo-Explorer":1858,"Aetherbind-Archmage":1776,"ZNS-Gift-Card-Collector":1770,"Invite-Badge":1736,"Scroll-Galaxy-Ninja":1624,"Vessel-LP":1606,"Scroll-Sloth-Badge":1539,"NFTs2Me-Silver-Pin-Badge":1379,"Meta-Map-Expeditor-Badge":1327,"Senior-Scroll-Explorer":1316,"Early-Bird-Owl":1161,"Nuri-Locker-Badge-(100)":1133,"SyncSwap-Master":1096,"Z-Protocol-Pioneer":1017,"Grade-POP-Badge":983,"Diamond-Hands-Owl":938,"NFTs2Me-Gold-Pin-Badge":926,"Scroll-Overlord":808,"Loop-Aficionado-Scroll":592,"Vessel-Explorer":571,"Varonve-Minter":473,"VenisterX-Badge":395,"Ducks-Club-Badge":369,"Benmo-Community-Badge":314,"GBadge":184,"Nuri-Locker-Badge-(200)":179,"GNFT-Staker-Badge":158,"Ambient-Yeet":123,"Nuri-Locker-Badge-(500)":105,"Diamond-Scroll-Bridger-Badge":64,"Nuri-Locker-Badge-(1000)":62,"Hippo-Badge":41,"GNFT-Whale":24,"Nuri-Locker-Badge-(5000)":19,"Nuri-Locker-Badge-(10000)":17,"Varonve-Holder":0,"Rho-Keeper":0}